mypackage_at1/__init__.py
mypackage_at1/mymodule.py
at_package_scan-0.1.0.dist-info/METADATA
at_package_scan-0.1.0.dist-info/WHEEL
at_package_scan-0.1.0.dist-info/top_level.txt
at_package_scan-0.1.0.dist-info/RECORD
