Metadata-Version: 2.2
Name: at_package_scan
Version: 0.1.0
Summary: A Python package with a submodule
Home-page: https://github.ibm.com/ANNIE-THOMAS1/sample_building_blocks
Author: Annie Thomas
Author-email: Annie Thomas <annie.thomas1@ibm.com>
Requires-Python: >=3.6
Dynamic: author
Dynamic: home-page
Dynamic: requires-python
